{"GeneratedCodeFiles":[],"GeneratedXamlFiles":["C:\\Users\\fabia\\RiderProjects\\MauiApp3\\MauiApp3\\obj\\Debug\\net8.0-windows10.0.19041.0\\win10-x64\\Platforms\\Windows\\App.xaml"],"GeneratedXbfFiles":["C:\\Users\\fabia\\RiderProjects\\MauiApp3\\MauiApp3\\obj\\Debug\\net8.0-windows10.0.19041.0\\win10-x64\\Platforms\\Windows\\App.xbf"],"GeneratedXamlPagesFiles":[],"MSBuildLogEntries":[{"SubCategory":null,"ErrorCode":null,"HelpKeyword":null,"File":null,"LineNumber":0,"ColumnNumber":0,"EndLineNumber":0,"EndColumnNumber":0,"Message":"Xaml Compiler Marker: 09:03:40: 939 perfXC_StartPass2, MauiApp3"},{"SubCategory":null,"ErrorCode":null,"HelpKeyword":null,"File":null,"LineNumber":0,"ColumnNumber":0,"EndLineNumber":0,"EndColumnNumber":0,"Message":"Xaml Compiler Marker: 09:03:40: 964 perfXC_FingerprintCheck, Using managed HashForWinMD"},{"SubCategory":null,"ErrorCode":null,"HelpKeyword":null,"File":null,"LineNumber":0,"ColumnNumber":0,"EndLineNumber":0,"EndColumnNumber":0,"Message":"Xaml Compiler Marker: 09:03:41:  84 perfXC_RestoredGeneratedPass2CodeFileBackup"},{"SubCategory":null,"ErrorCode":null,"HelpKeyword":null,"File":null,"LineNumber":0,"ColumnNumber":0,"EndLineNumber":0,"EndColumnNumber":0,"Message":"Xaml Compiler Marker: 09:03:41:  91 perfXC_RestoredTypeInfoBackup"}]}